cognitive_shell/__init__.py
cognitive_shell/__main__.py
cognitive_shell/quick_start.py
neuronet_ai_cognitiveshell-0.2.6.dist-info/licenses/LICENSE
neuronet_ai_cognitiveshell-0.2.6.dist-info/METADATA
neuronet_ai_cognitiveshell-0.2.6.dist-info/WHEEL
neuronet_ai_cognitiveshell-0.2.6.dist-info/entry_points.txt
neuronet_ai_cognitiveshell-0.2.6.dist-info/top_level.txt
neuronet_ai_cognitiveshell-0.2.6.dist-info/RECORD
