Metadata-Version: 2.4
Name: neuronet-ai-cognitiveshell
Version: 0.2.6
Summary: Semi-Agentic Terminal AI assistant with shell error detection and debugging via Telegram
Home-page: https://github.com/muhammad-robitulloh/NeuroNet-AI-NodeSystem_Cognitive-Shell.v2.0
Author: Muhammad Robitulloh
Author-email: muhammadrobitulloh19@gmail.com
Classifier: Programming Language :: Python :: 3
Classifier: License :: OSI Approved :: MIT License
Classifier: Operating System :: POSIX :: Linux
Requires-Python: >=3.7
License-File: LICENSE
Requires-Dist: python-telegram-bot>=20.0
Requires-Dist: python-dotenv>=0.21.0
Requires-Dist: pexpect>=4.8
Requires-Dist: requests>=2.25
Requires-Dist: pytz>=2022.1
Dynamic: author
Dynamic: author-email
Dynamic: classifier
Dynamic: description
Dynamic: description-content-type
Dynamic: home-page
Dynamic: license-file
Dynamic: requires-dist
Dynamic: requires-python
Dynamic: summary
